veh
