Metadata-Version: 1.0
Name: veh
Version: 0.93.0
Summary: virtualenv for hg
Home-page: http://github.com/nicferrier/veh
Author: Nic Ferrier
Author-email: nic@ferrier.me.uk
License: GNU GPL v3
Download-URL: http://github.com/nicferrier/veh/downloads
Platform: any
Classifier: Development Status :: 3 - Alpha
Classifier: Intended Audience :: Developers
Classifier: License :: OSI Approved :: GNU General Public License (GPL)
Classifier: Operating System :: OS Independent
Classifier: Programming Language :: Python
Classifier: Topic :: Utilities
